jacobi_driver_simulated.cpython-312-darwin.so
libjacobi-simulated-driver.dylib
jacobi_simulated_driver-1.1.21.dist-info/RECORD
jacobi_simulated_driver-1.1.21.dist-info/WHEEL
jacobi_simulated_driver-1.1.21.dist-info/METADATA
jacobi_simulated_driver-1.1.21.dist-info/licenses/LICENSE
