Metadata-Version: 2.2
Name: jacobi-simulated-driver
Version: 1.1.21
Summary: Driver for Simulated Robots.
Keywords: robotics,robot-driver,driver,studio
Author-Email: Jacobi Robotics <lars.berscheid@jacobirobotics.com>
License: Copyright (c) 2022-2024 Jacobi Robotics Inc.
Classifier: Development Status :: 5 - Production/Stable
Classifier: Intended Audience :: Science/Research
Classifier: Topic :: Scientific/Engineering
Classifier: License :: Other/Proprietary License
Classifier: Programming Language :: C++
Project-URL: homepage, https://www.jacobirobotics.com
Project-URL: documentation, https://docs.jacobirobotics.com
Requires-Python: >=3.10
Requires-Dist: jacobi-motion>=1.1.21
